pymp/__init__.py
pymp/globals.py
pymp/transforms.py
pymp/data/PHY25MR2_TestPlan_01_20150604142614.bin
pymp/data/PHY25MR2_TestPlan_01_20150604142614.txt
pymp/data/PHY25MR2_TestPlan_02_20150604142614.bin
pymp/data/PHY27MR2_TestPlan_03_20180830154128.bin
pymp/data/XIM_0001.xim
pymp/data/wl/RI.1.2.246.352.62.1.4734329381690150072.16107155259054159750.dcm
pymp/data/wl/RI.1.2.246.352.62.1.4762383955568555982.18293644309891020946.dcm
pymp/data/wl/RI.1.2.246.352.62.1.4836273358382822620.11691083385093600696.dcm
pymp/data/wl/RI.1.2.246.352.62.1.4973926530411171260.11903223280751265411.dcm
pymp/data/wl/RI.1.2.246.352.62.1.5081191942223899240.6722756222624198813.dcm
pymp/data/wl/RI.1.2.246.352.62.1.5167792181464040937.14919137077179553190.dcm
pymp/data/wl/RI.1.2.246.352.62.1.5478722064245565177.2058124167527870882.dcm
pymp/data/wl/RI.1.2.246.352.62.1.5715921983785070412.11470947625597952936.dcm
pymp/frames/__init__.py
pymp/frames/base.py
pymp/frames/ndframe.py
pymp/pmodels/__init__.py
pymp/pmodels/geometric.py
pymp/test/test_frames.py
pymp/test/test_vms_log.py
pymp/vms/__init__.py
pymp/vms/image/__init__.py
pymp/vms/image/xim.py
pymp/vms/log/__init__.py
pymp/vms/log/definitions.py
pymp/vms/log/header.py
pymp/vms/log/subbeam.py
pymp/vms/log/trajectory.py
pymp-0.0.2.dist-info/LICENSE
pymp-0.0.2.dist-info/METADATA
pymp-0.0.2.dist-info/WHEEL
pymp-0.0.2.dist-info/top_level.txt
pymp-0.0.2.dist-info/RECORD
