Metadata-Version: 2.1
Name: pymp
Version: 0.0.2
Summary: A small package of medical physics toys
Home-page: https://github.com/tallhamer/pymp
Author: Michael J Tallhamer MSc DABR
Author-email: mike.tallhamer@gmail.com
License: UNKNOWN
Platform: UNKNOWN
Classifier: Programming Language :: Python :: 3
Classifier: License :: OSI Approved :: MIT License
Classifier: Operating System :: OS Independent
